safeai/__init__.py
safeai/__version__.py
safeai/analyzer.py
safeai/cli.py
safeai/rules/__init__.py
safeai/rules/base.py
safeai/rules/python_rules.py
safeai/utils/__init__.py
safeai/utils/ast_helper.py
safeai/utils/file_loader.py
safeai/utils/formatter.py
safeai_scanner-0.1.1.dist-info/METADATA
safeai_scanner-0.1.1.dist-info/WHEEL
safeai_scanner-0.1.1.dist-info/entry_points.txt
safeai_scanner-0.1.1.dist-info/licenses/LICENSE
safeai_scanner-0.1.1.dist-info/RECORD
