Metadata-Version: 2.4
Name: safeai-scanner
Version: 0.1.1
Summary: Security analyzer for AI-generated code
Project-URL: Homepage, https://github.com/whickybravo388/safeai
Project-URL: Repository, https://github.com/whickybravo388/safeai
Project-URL: Issues, https://github.com/whickybravo388/safeai/issues
Author-email: Den Ignatov <whickybravo388@gmail.com>
License: MIT
License-File: LICENSE
Keywords: ai,code-analysis,security,vulnerability-scanner
Classifier: Development Status :: 4 - Beta
Classifier: Intended Audience :: Developers
Classifier: License :: OSI Approved :: MIT License
Classifier: Operating System :: OS Independent
Classifier: Programming Language :: Python :: 3
Classifier: Programming Language :: Python :: 3.9
Classifier: Programming Language :: Python :: 3.10
Classifier: Programming Language :: Python :: 3.11
Classifier: Programming Language :: Python :: 3.12
Classifier: Topic :: Security
Classifier: Topic :: Software Development :: Quality Assurance
Requires-Python: >=3.9
Requires-Dist: rich>=13.0.0
